image_rect/None.py
image_rect/__init__.py
image_rect/_nbdev.py
image_rect/image_rect.py
image_rect-0.0.4.dist-info/LICENSE
image_rect-0.0.4.dist-info/METADATA
image_rect-0.0.4.dist-info/WHEEL
image_rect-0.0.4.dist-info/entry_points.txt
image_rect-0.0.4.dist-info/top_level.txt
image_rect-0.0.4.dist-info/RECORD
