Metadata-Version: 2.1
Name: image-rect
Version: 0.0.4
Summary: Image Rectification with pytorch
Home-page: https://github.com/justinblaber/image_rect/tree/master/
Author: Justin Blaber
Author-email: justin.akira.blaber@gmail.com
License: Apache Software License 2.0
Keywords: image rectification
Platform: UNKNOWN
Classifier: Development Status :: 3 - Alpha
Classifier: Intended Audience :: Developers
Classifier: License :: OSI Approved :: Apache Software License
Classifier: Natural Language :: English
Classifier: Programming Language :: Python :: 3.6
Classifier: Programming Language :: Python :: 3.7
Classifier: Programming Language :: Python :: 3.8
Requires-Python: >=3.6
